connPFM/__init__.py
connPFM/_version.py
connPFM/connPFM.py
connPFM/due.py
connPFM/info.py
connPFM/connectivity/__init__.py
connPFM/connectivity/connectivity_utils.py
connPFM/connectivity/ev.py
connPFM/connectivity/plotting.py
connPFM/debiasing/__init__.py
connPFM/debiasing/debiasing.py
connPFM/debiasing/debiasing_functions.py
connPFM/deconvolution/__init__.py
connPFM/deconvolution/compute_slars.py
connPFM/deconvolution/roiPFM.py
connPFM/deconvolution/stability_lars.py
connPFM/deconvolution/stability_lars_caller.py
connPFM/tests/__init__.py
connPFM/tests/conftest.py
connPFM/tests/test_debiasing.py
connPFM/tests/test_deconvolution.py
connPFM/tests/test_ev.py
connPFM/tests/test_integration.py
connPFM/tests/test_utils.py
connPFM-0.0.2.dist-info/LICENSE
connPFM-0.0.2.dist-info/METADATA
connPFM-0.0.2.dist-info/WHEEL
connPFM-0.0.2.dist-info/entry_points.txt
connPFM-0.0.2.dist-info/top_level.txt
connPFM-0.0.2.dist-info/RECORD
